{"chunk_definitions":[{"chunk_id":"csetup_chunk","chunk_label":"setup","document_id":"DF0FDF0F","expansion_state":0,"options":{"engine":"r","include":false,"label":"setup"},"row":17,"row_count":1,"visible":true},{"chunk_id":"cgjqs4eawwl77","chunk_label":"unnamed-chunk-1","document_id":"DF0FDF0F","expansion_state":0,"options":{"engine":"r","label":"unnamed-chunk-4"},"row":25,"row_count":1,"visible":true},{"chunk_id":"c0s38txjfzrgb","chunk_label":"unnamed-chunk-2","document_id":"DF0FDF0F","expansion_state":0,"options":{"engine":"r","label":"unnamed-chunk-26"},"row":40,"row_count":1,"visible":true},{"chunk_id":"csrbvag4uneyy","chunk_label":"unnamed-chunk-3","document_id":"DF0FDF0F","expansion_state":0,"options":{"engine":"r","label":"unnamed-chunk-20"},"row":49,"row_count":1,"visible":true},{"chunk_id":"cvtbgnxsudcvd","chunk_label":"unnamed-chunk-4","document_id":"DF0FDF0F","expansion_state":0,"options":{"engine":"r","label":"unnamed-chunk-22"},"row":54,"row_count":1,"visible":true},{"chunk_id":"cadxscwl9y5l0","chunk_label":"unnamed-chunk-5","document_id":"DF0FDF0F","expansion_state":0,"options":{"engine":"r","label":"unnamed-chunk-36"},"row":60,"row_count":1,"visible":true},{"chunk_id":"csgmq8fz2cfka","chunk_label":"unnamed-chunk-6","document_id":"DF0FDF0F","expansion_state":0,"options":{"engine":"r","label":"unnamed-chunk-39"},"row":67,"row_count":1,"visible":true},{"chunk_id":"c0hvvaoqfdn93","chunk_label":"unnamed-chunk-7","document_id":"DF0FDF0F","expansion_state":0,"options":{"engine":"r","label":"unnamed-chunk-90"},"row":80,"row_count":1,"visible":true},{"chunk_id":"crcnkrktx8dgp","chunk_label":"unnamed-chunk-8","document_id":"DF0FDF0F","expansion_state":0,"options":{"engine":"r","label":"unnamed-chunk-61"},"row":88,"row_count":1,"visible":true},{"chunk_id":"cccp6zwu6wta0","chunk_label":"unnamed-chunk-9","document_id":"DF0FDF0F","expansion_state":0,"options":{"engine":"r","label":"unnamed-chunk-170"},"row":108,"row_count":1,"visible":true},{"chunk_id":"ch7ucovs3jgjg","chunk_label":"unnamed-chunk-10","document_id":"DF0FDF0F","expansion_state":0,"options":{"engine":"r","label":"unnamed-chunk-180"},"row":125,"row_count":1,"visible":true},{"chunk_id":"c2tqmh65kf4l4","chunk_label":"unnamed-chunk-11","document_id":"DF0FDF0F","expansion_state":0,"options":{"engine":"r","label":"unnamed-chunk-179"},"row":144,"row_count":1,"visible":true}],"chunk_rendered_width":700,"default_chunk_options":{"error":false},"doc_write_time":1572907070,"working_dir":null}